madvr/__init__.py
madvr/commands.py
madvr/errors.py
madvr/madvr.py
tests/__init__.py
tests/testMadVR.py
py_madvr-1.4.8.dist-info/LICENSE
py_madvr-1.4.8.dist-info/METADATA
py_madvr-1.4.8.dist-info/WHEEL
py_madvr-1.4.8.dist-info/top_level.txt
py_madvr-1.4.8.dist-info/RECORD
