Metadata-Version: 2.1
Name: py-madvr
Version: 1.4.8
Summary: A package to control MadVR Envy over IP
Home-page: https://github.com/iloveicedgreentea/py-madvr
Author: iloveicedgreentea
Classifier: Programming Language :: Python :: 3.9
Classifier: License :: OSI Approved :: MIT License
Classifier: Operating System :: OS Independent
License-File: LICENSE
